dianpy/__init__.py
dianpy/athlete.py
dianpy/event.py
dianpy/meet.py
dianpy-1.0.5.dist-info/METADATA
dianpy-1.0.5.dist-info/WHEEL
dianpy-1.0.5.dist-info/RECORD
