Metadata-Version: 2.4
Name: dianpy
Version: 1.0.5
Summary: DianPy a special parser for working with the dian scoreboard
Author: LordCode
Author-email: 9999269010dddd@gmail.com
Requires-Python: >=3.11,<4.0
Classifier: Programming Language :: Python :: 3
Classifier: Programming Language :: Python :: 3.11
Classifier: Programming Language :: Python :: 3.12
Classifier: Programming Language :: Python :: 3.13
Classifier: Programming Language :: Python :: 3.14
Requires-Dist: lxml (>=6.0.2)
Requires-Dist: pydantic-xml (>=2.18.0)
